[
   {
      "id": 1,
      "nombre": "tabla-28cm",
      "precio": "000",
      "descuento": true,
      "descripcion": "Neque porro quisquam est qui dolorem ipsum quia dolor sit amet, consectetur, adipisci velit...",
      "marca": "trademark",
      "categoria": "utensilios",
      "material": "madera",
      "imagen": "tabla-28-cm-bamboo-1.jpg"
   },
   {
      "id": 2,
      "nombre": "pincel",
      "precio": "000",
      "descuento": true,
      "descripcion": "Neque porro quisquam est qui dolorem ipsum quia dolor sit amet, consectetur, adipisci velit...",
      "marca": "trademark",
      "categoria": "utensilios",
      "material": "silicona",
      "imagen": "pincel-silicon-gourmet-2.jpg"
   },
   {
      "id": 3,
      "nombre": "espumadera",
      "precio": "000",
      "descuento": false,
      "descripcion": "Neque porro quisquam est qui dolorem ipsum quia dolor sit amet, consectetur, adipisci velit...",
      "marca": "trademark",
      "categoria": "utensilios",
      "material": "acero",
      "imagen": "espumadera-acero-1.jpg"
   },
   {
      "id": 4,
      "nombre": "cuchara para helado",
      "precio": "000",
      "descuento": false,
      "descripcion": "Neque porro quisquam est qui dolorem ipsum quia dolor sit amet, consectetur, adipisci velit...",
      "marca": "trademark",
      "categoria": "utensilios",
      "material": "plastico",
      "imagen": "cuchara-para-helado-black-1.jpg"
   },
   {
      "id": 5,
      "nombre": "batidor",
      "precio": "000",
      "descuento": true,
      "descripcion": "Neque porro quisquam est qui dolorem ipsum quia dolor sit amet, consectetur, adipisci velit...",
      "marca": "trademark",
      "categoria": "utensilios",
      "material": "acero",
      "imagen": "batidor-acero-1.jpg"
   },
   {
      "id": 6,
      "nombre": "lorem ipsum",
      "precio": "000",
      "descuento": true,
      "descripcion": "Neque porro quisquam est qui dolorem ipsum quia dolor sit amet, consectetur, adipisci velit...",
      "marca": "trademark",
      "categoria": "aromaticos",
      "material": "plastico",
      "imagen": ""
   },
   {
      "id": 7,
      "nombre": "home spray",
      "precio": "000",
      "descuento": true,
      "descripcion": "Neque porro quisquam est qui dolorem ipsum quia dolor sit amet, consectetur, adipisci velit...",
      "marca": "trademark",
      "categoria": "aromaticos",
      "material": "plastico",
      "imagen": "home-spray-vain-cedr-1.jpg"
   },
   {
      "id": 8,
      "nombre": "lata emporium",
      "precio": "000",
      "descuento": true,
      "descripcion": "Neque porro quisquam est qui dolorem ipsum quia dolor sit amet, consectetur, adipisci velit...",
      "marca": "trademark",
      "categoria": "aromaticos",
      "material": "acero",
      "imagen": "lata-emporium-labrad-esp-1.jpg"
   },
   {
      "id": 9,
      "nombre": "vela aromatica The candle shop",
      "precio": "000",
      "descuento": false,
      "descripcion": "Neque porro quisquam est qui dolorem ipsum quia dolor sit amet, consectetur, adipisci velit...",
      "marca": "trademark",
      "categoria": "aromaticos",
      "material": "vela",
      "imagen": "vela-aromatica-tin-the-candle-shop-1.jpg"
   },
   {
      "id": 10,
      "nombre": "difusor aromatico",
      "precio": "000",
      "descuento": true,
      "descripcion": "Neque porro quisquam est qui dolorem ipsum quia dolor sit amet, consectetur, adipisci velit...",
      "marca": "trademark",
      "categoria": "aromaticos",
      "material": "vidrio",
      "imagen": "difusor-de-ambiente--glossy-the-candle-shop-1.jpg"
   },
   {
      "id": 11,
      "nombre": "canasto",
      "precio": "000",
      "descuento": true,
      "descripcion": "Neque porro quisquam est qui dolorem ipsum quia dolor sit amet, consectetur, adipisci velit...",
      "marca": "trademark",
      "categoria": "deco",
      "material": "yute",
      "imagen": "canasto-yute-tejido-23-cm-1.jpg"
   },
   {
      "id": 12,
      "nombre": "reloj de pared",
      "precio": "000",
      "descuento": true,
      "descripcion": "Neque porro quisquam est qui dolorem ipsum quia dolor sit amet, consectetur, adipisci velit...",
      "marca": "trademark",
      "categoria": "deco",
      "material": "plastico",
      "imagen": "reloj-brooklin-30-cm-1.jpg"
   },
   {
      "id": 13,
      "nombre": "florero",
      "precio": "000",
      "descuento": true,
      "descripcion": "Neque porro quisquam est qui dolorem ipsum quia dolor sit amet, consectetur, adipisci velit...",
      "marca": "trademark",
      "categoria": "deco",
      "material": "vidrio",
      "imagen": "florero-vidrio-clasico-20-cm-1.jpg"
   },
   {
      "id": 14,
      "nombre": "reloj de mesa",
      "precio": "000",
      "descuento": true,
      "descripcion": "Neque porro quisquam est qui dolorem ipsum quia dolor sit amet, consectetur, adipisci velit...",
      "marca": "trademark",
      "categoria": "deco",
      "material": "metal",
      "imagen": "reloj-mesa-metal-rosa-19-cm-1.jpg"
   },
   {
      "id": 15,
      "nombre": "lorem ipsum",
      "precio": "000",
      "descuento": true,
      "descripcion": "Neque porro quisquam est qui dolorem ipsum quia dolor sit amet, consectetur, adipisci velit...",
      "marca": "trademark",
      "categoria": "deco",
      "material": "cuerda y vidrio",
      "imagen": "fanal-cuerda-y-vidrio-28-cm-1.jpg"
   },
   {
      "id": 16,
      "nombre": "frasco hermetico",
      "precio": "000",
      "descuento": true,
      "descripcion": "Neque porro quisquam est qui dolorem ipsum quia dolor sit amet, consectetur, adipisci velit...",
      "marca": "trademark",
      "categoria": "frascos",
      "material": "vidrio",
      "imagen": "frasco-hermetico-tapa-vison-1.jpg"
   },
   {
      "id": 17,
      "nombre": "frasco de vidrio y mimbre",
      "precio": "000",
      "descuento": true,
      "descripcion": "Neque porro quisquam est qui dolorem ipsum quia dolor sit amet, consectetur, adipisci velit...",
      "marca": "trademark",
      "categoria": "frascos",
      "material": "vidrio y mimbre",
      "imagen": "frasco-vidrio-mimbre-1,5-l-1.jpg"
   },
   {
      "id": 18,
      "nombre": "frasco 5l.",
      "precio": "000",
      "descuento": false,
      "descripcion": "Neque porro quisquam est qui dolorem ipsum quia dolor sit amet, consectetur, adipisci velit...",
      "marca": "trademark",
      "categoria": "frascos",
      "material": "vidrio",
      "imagen": "frasco-mason-4-5-lt-1.jpg"
   },
   {
      "id": 19,
      "nombre": "jarro termico",
      "precio": "000",
      "descuento": true,
      "descripcion": "Neque porro quisquam est qui dolorem ipsum quia dolor sit amet, consectetur, adipisci velit...",
      "marca": "trademark",
      "categoria": "jarras",
      "material": "vidrio",
      "imagen": "jarro-termico-bodum-45-cc-1.jpg"
   },
   {
      "id": 20,
      "nombre": "jarra termica",
      "precio": "000",
      "descuento": true,
      "descripcion": "Neque porro quisquam est qui dolorem ipsum quia dolor sit amet, consectetur, adipisci velit...",
      "marca": "trademark",
      "categoria": "jarras",
      "material": "acrilico",
      "imagen": "jarra-termica-ng-1.jpg"
   },
   {
      "id": 21,
      "nombre": "jarra acrilico hammered",
      "precio": "000",
      "descuento": false,
      "descripcion": "Neque porro quisquam est qui dolorem ipsum quia dolor sit amet, consectetur, adipisci velit...",
      "marca": "trademark",
      "categoria": "jarras",
      "material": "acrilico",
      "imagen": "jarra-acril-hammered-1-2lt-1.jpg"
   },
   {
      "id": 22,
      "nombre": "jarro termico",
      "precio": "000",
      "descuento": true,
      "descripcion": "Neque porro quisquam est qui dolorem ipsum quia dolor sit amet, consectetur, adipisci velit...",
      "marca": "trademark",
      "categoria": "jarras",
      "material": "acero",
      "imagen": "jarro-termico-bodum-35-cc-1.jpg"
   },
   {
      "id": 23,
      "nombre": "vaso doble",
      "precio": "000",
      "descuento": true,
      "descripcion": "Neque porro quisquam est qui dolorem ipsum quia dolor sit amet, consectetur, adipisci velit...",
      "marca": "trademark",
      "categoria": "vasos",
      "material": "vidrio",
      "imagen": "vaso-doble-vidrio-450-cc-1.jpg"
   },
   {
      "id": 24,
      "nombre": "vaso para whiskey",
      "precio": "000",
      "descuento": false,
      "descripcion": "Neque porro quisquam est qui dolorem ipsum quia dolor sit amet, consectetur, adipisci velit...",
      "marca": "trademark",
      "categoria": "vasos",
      "material": "vidrio",
      "imagen": "vaso-eclipse-whisky-lfp-1.jpg"
   },
   {
      "id": 25,
      "nombre": "vaso alto Sidney",
      "precio": "000",
      "descuento": false,
      "descripcion": "Neque porro quisquam est qui dolorem ipsum quia dolor sit amet, consectetur, adipisci velit...",
      "marca": "trademark",
      "categoria": "vasos",
      "material": "acrilico",
      "imagen": "vaso-alto-acril-scales-fume-g-2.jpg"
   },
   {
      "id": 26,
      "nombre": "set posavasos",
      "precio": "000",
      "descuento": true,
      "descripcion": "Neque porro quisquam est qui dolorem ipsum quia dolor sit amet, consectetur, adipisci velit...",
      "marca": "trademark",
      "categoria": "vasos",
      "material": "plastico",
      "imagen": "set-posavasos-hexagonal-x-4-piezas-1.jpg"
   },
   {
      "id": 27,
      "name": "Florero",
      "price": 3500,
      "discount": 15,
      "description": "Florero clásico chico de vidrio",
      "marca": "otro",
      "section": "vidrio",
      "imagen": null
   }
]